MANIFEST.in
README.md
setup.cfg
setup.py
django_rest_framework_base64_fields/__init__.py
django_rest_framework_base64_fields/fields.py
django_rest_framework_base64_fields.egg-info/PKG-INFO
django_rest_framework_base64_fields.egg-info/SOURCES.txt
django_rest_framework_base64_fields.egg-info/dependency_links.txt
django_rest_framework_base64_fields.egg-info/not-zip-safe
django_rest_framework_base64_fields.egg-info/requires.txt
django_rest_framework_base64_fields.egg-info/top_level.txt